cz_changeup/__init__.py
cz_changeup/cz_changeup.py
cz_changeup/templates/CHANGELOG.md.j2
cz_changeup-1.1.2.dist-info/METADATA
cz_changeup-1.1.2.dist-info/WHEEL
cz_changeup-1.1.2.dist-info/entry_points.txt
cz_changeup-1.1.2.dist-info/licenses/LICENSE
cz_changeup-1.1.2.dist-info/RECORD
