Metadata-Version: 2.4
Name: cz-changeup
Version: 1.1.2
Summary: Commitizen plugin for better changelog generation
Project-URL: Changelog, https://github.com/kmnhan/cz-changeup/blob/main/CHANGELOG.md
Project-URL: Documentation, https://github.com/kmnhan/cz-changeup#readme
Project-URL: Issues, https://github.com/kmnhan/cz-changeup/issues
Project-URL: Source, https://github.com/kmnhan/cz-changeup
Author-email: Kimoon Han <khan@kaist.ac.kr>
License-Expression: MIT
License-File: LICENSE
Keywords: changelog,commitizen
Classifier: Development Status :: 4 - Beta
Classifier: Intended Audience :: Developers
Classifier: License :: OSI Approved :: MIT License
Classifier: Natural Language :: English
Classifier: Operating System :: OS Independent
Classifier: Programming Language :: Python
Classifier: Programming Language :: Python :: 3.9
Classifier: Programming Language :: Python :: 3.10
Classifier: Programming Language :: Python :: 3.11
Classifier: Programming Language :: Python :: 3.12
Requires-Python: >=3.9
Requires-Dist: commitizen<5.0.0,>=3.0.0
